{
  "video_uri": "${${Cams}}",
  "video_uri_defaults": {
    "Cams": "CamsAll",
    "CamsAll": "thread:\/\/join:[sync_tolerance_us=4000]\/\/{${CamsSlamFrontR}}{${CamsSlamSideR}}{${CamsSlamFrontL}}{${CamsSlamSideL}}",

    "period25fps": "5000",
    "ExposureTime25fps": "1000",
    "CamsETL25fps": "thread:\/\/eyes:[size=636x400,sn=574018304,ExternalTrigger=1,CenteredExposure=1,period=${period25fps},ExposureTime=${ExposureTime25fps}]\/\/\/",
    "CamsETR25fps": "thread:\/\/eyes:[size=636x400,sn=152191745,ExternalTrigger=1,CenteredExposure=1,period=${period25fps},ExposureTime=${ExposureTime25fps}]\/\/\/"
  }
}
